[
  {
    "name": "Ali",
    "lastname": "Ahmadi",
    "passport": "A12345678",
    "clientNumber": "987654321",
    "birthdate": "1990-01-15",
    "pdfLink": "https://drive.google.com/file/d/1frpSOrMpOYgVP61UakjiZeAv5F_y8-Qs/view?usp=drive_link"
  },
  {
    "name": "Fatemeh",
    "lastname": "Karimi",
    "passport": "B98765432",
    "clientNumber": "123456789",
    "birthdate": "1992-06-22",
    "pdfLink": "https://drive.google.com/file/d/1AeILY5xoS1WWdVTXFde4KFAl4mm5ADLr/view?usp=drive_link"
  }
]
